<!-- This is a generated file. Do not edit manually or suffer the consequences... -->
<strings>
    <!-- Drawables -->
    <string id="MeterLeft">Left meter</string>
    <string id="MeterRight">Right meter</string>

    <!-- Behaviors -->
    <string id="MeterBehaviorBattery">Battery charge</string>
    <string id="MeterBehaviorFloorsClimbed">Floors climbed</string>
    <string id="MeterBehaviorSteps">Steps stepped</string>
    <string id="MeterBehaviorMoveBar">Move bar</string>
    <string id="MeterBehaviorActiveMinutes">Activ</string>
</strings>
