<!-- This is a generated file. Do not edit manually or suffer the consequences... -->
<strings>
    <string id="Theme0">Black Treacle</string>
    <string id="Theme1">White Blank Page</string>
    <string id="Theme2">Red Flag</string>
    <string id="Theme3">Jack-in-the-Green</string>
    <string id="Theme4">Behind Blue Eyes</string>
    <string id="Theme5">Old Yellow Bricks</string>
    <string id="Theme6">Pretty Pink Rose</string>
    <string id="Theme7">Forever in Blue Greens</string>
    <string id="Theme8">Pink Fluffy Unicorns</string>
</strings>
